sstc_st/__init__.py
sstc_st/version.py
sstc_st-0.1.3.dist-info/METADATA
sstc_st-0.1.3.dist-info/WHEEL
sstc_st-0.1.3.dist-info/RECORD
