Metadata-Version: 2.1
Name: sstc-st
Version: 0.1.3
Summary: SSTC Streamlit toolbox
Author: Jobelund
Author-email: 124563223+jobelund@users.noreply.github.com
Requires-Python: >=3.11,<4.0
Classifier: Programming Language :: Python :: 3
Classifier: Programming Language :: Python :: 3.11
Classifier: Programming Language :: Python :: 3.12
Requires-Dist: mkdocs (>=1.5.3,<2.0.0)
Requires-Dist: pytest (>=7.4.3,<8.0.0)
Requires-Dist: pyyaml (>=6.0.1,<7.0.0)
Requires-Dist: streamlit (>=1.29.0,<2.0.0)
